{
    "sample_id": "atomic-layer-etching/experimental-usecase/17/figure_2",
    "classification": {
        "a": "line chart"
    },
    "summarization": {
        "a": "This line chart presents mass change data during Al\u2082O\u2083 atomic layer etching (ALE) at 200\u00b0C, showing stepwise decreases in mass following alternating exposures to SF\u2084 and Sn(acac)\u2082. Distinct mass loss events (\u0394M) occur upon each SF\u2084 pulse, indicating volatile byproduct formation from fluorination. The subsequent Sn(acac)\u2082 exposures yield mass gains, consistent with precursor adsorption. The black dashed arrow labeled MCPC highlights a stable mass plateau following precursor saturation, marking the point of maximum chemisorbed precursor coverage."
    },
    "data_extraction": {
        "a": "| Time (s) | Mass Change (ng/cm\u00b2) |\n|----------|----------------------|\n| 13700    | -250                 |\n| 13720    | -255                 |\n| 13740    | -257                 |\n| 13760    | -258                 |\n| 13780    | -260                 |\n| 13800    | -263                 |\n| 13820    | -265                 |\n| 13840    | -266                 |\n| 13860    | -268                 |\n| 13880    | -269                 |\n| 13900    | -270                 |"
    },
    "vqa": {
        "a": [
            {
                "question_type": "Process-Oriented",
                "question": "Does the mass increase after Sn(acac)\u2082 exposure?",
                "answer_type": "Yes/No",
                "answer": "Yes"
            },
            {
                "question_type": "Structure-Property",
                "question": "What does the label MCPC represent in this ALE process?",
                "answer_type": "Factoid",
                "answer": "MCPC refers to the Maximum Chemisorbed Precursor Coverage."
            },
            {
                "question_type": "Application/Performance",
                "question": "What is the function of SF\u2084 and Sn(acac)\u2082 in this etch sequence?",
                "answer_type": "List",
                "answer": "SF\u2084 removes surface oxygen , Sn(acac)\u2082 replenishes surface metal sites"
            },
            {
                "question_type": "Comparative/Trend",
                "question": "How does the mass profile reflect the self-limiting nature of ALE?",
                "answer_type": "Paragraph",
                "answer": "The mass profile displays repeated and saturating steps, where each pulse of SF\u2084 causes a predictable mass loss (etch step), followed by a stable plateau after Sn(acac)\u2082 adsorption. The return to similar mass levels after each Sn(acac)\u2082 exposure indicates that surface sites become fully occupied and no further mass uptake occurs until the next etch step. This cyclical pattern, along with the MCPC plateau, supports the self-limiting mechanism characteristic of ALE, ensuring precise and controlled etch per cycle behaviour."
            }
        ]
    },
    "bbox": {
        "a": {
            "x": 0,
            "y": 0,
            "width": 669,
            "height": 539
        }
    }
}