{
    "sample_id": "atomic-layer-deposition/experimental-usecase/8/figure_8",
    "classification": {
        "a": "conceptual diagram",
        "b": "conceptual diagram"
    },
    "summarization": {
        "a": "The schematic compares three ALD pulsing strategies, doping, homogeneous mixing, and nanolaminates, showing how different sequences of precursor A and precursor B cycles yield different film architectures.",
        "b": "A legend defines the color coding for precursor A, precursor B, co reactant, and purging steps used in the pulse sequence cartoons."
    },
    "data_extraction": {
        "a": "",
        "b": ""
    },
    "vqa": {
        "b": [
            {
                "question_type": "Structure-Property",
                "question": "In this conceptual figure, what structural feature distinguishes a homogeneous mixed film from a nanolaminate film?",
                "answer_type": "Factoid",
                "answer": "A homogeneous mixed film has A and B distributed throughout the thickness without discrete layers, whereas a nanolaminate has alternating A rich and B rich layers."
            },
            {
                "question_type": "Process-Oriented",
                "question": "What do the black blocks in the pulse sequence cartoons represent?",
                "answer_type": "Factoid",
                "answer": "Purging steps."
            }
        ],
        "a": [
            {
                "question_type": "Process-Oriented",
                "question": "How does changing the ordering of precursor A and precursor B cycles enable doping versus nanolaminate formation in ALD?",
                "answer_type": "Paragraph",
                "answer": "In the doping style sequence, precursor B is inserted only occasionally among many precursor A cycles, so B contributes a low fraction of the incorporated cations and is distributed within an A rich matrix. In a nanolaminate sequence, blocks of A cycles and blocks of B cycles are repeated, which builds an intentional layered stacking. Because ALD is surface controlled, the sequence design is a primary lever for whether B is dispersed or segregated into layers."
            },
            {
                "question_type": "Comparative/Trend",
                "question": "Which strategy in panel (a) is most likely to create the sharpest A rich and B rich layer interfaces, homogeneous mixing or nanolaminates?",
                "answer_type": "Yes/No",
                "answer": "Nanolaminates"
            }
        ]
    },
    "bbox": {
        "b": {
            "x": 5,
            "y": 4,
            "width": 661,
            "height": 305
        },
        "a": {
            "x": 5,
            "y": 4,
            "width": 661,
            "height": 305
        }
    }
}