{
    "sample_id": "atomic-layer-deposition/simulation-usecase/53/figure_8",
    "classification": {
        "a": "multiple line chart",
        "b": "multiple line chart"
    },
    "summarization": {
        "a": "The line chart displays changes in \u0394E (kJ/mol) for  SiH2(NH2)2 on surface of three different species (SiH3-OH, SiH3-NH2, SiH3-NH-SiH3) across five states (UR, BR, TS, BP, UP).",
        "b": "The line chart shows changes in \u0394E (kJ/mol) for  SiH2DMA2 precursor on surface of three different species (SiH3-OH, SiH3-NH2, SiH3-NH-SiH3) across five states (UR, BR, TS, BP, UP)."
    },
    "data_extraction": {
        "a": "| Step | SiH\u2083\u2013OH | SiH\u2083\u2013NH\u2082 | SiH\u2083\u2013NH\u2013SiH\u2083 |\n|------|---------|----------|--------------|\n| UR   | 0       | 0        | 0            |\n| BR   | -40     | -20      | -15          |\n| TS   | +80     | +60      | +70          |\n| BP   | -60     | -30      | -25          |\n| UP   | -80     | -10      | -5           |",
        "b": "| Step | SiH\u2083\u2013OH | SiH\u2083\u2013NH\u2082 | SiH\u2083\u2013NH\u2013SiH\u2083 |\n|------|---------|----------|--------------|\n| UR   | 0       | 0        | 0            |\n| BR   | -35     | -18      | -15          |\n| TS   | +75     | +55      | +65          |\n| BP   | -55     | -28      | -25          |\n| UP   | -75     | -12      | -8           |"
    },
    "vqa": {
        "a": [
            {
                "question_type": "Process-Oriented",
                "question": "Are the energetics calculated for SiH2(NH2)2 and SiH2DMA2 precursors very similar ?",
                "answer_type": "Yes/No",
                "answer": "Yes"
            },
            {
                "question_type": "Comparative/Trend",
                "question": "Which reactions are exothermic?",
                "answer_type": "Paragraph",
                "answer": "The reactions leading to BR, BP and UP (optimized to local minima) on the SiH3\u2212OH model surface were calculated to be more exothermic than those on the SiH3\u2212NH2 and SiH3\u2212NH\u2212SiH3 systems, consistent with the results of the thermodynamic model"
            }
        ],
        "b": [
            {
                "question_type": "Process-Oriented",
                "question": "What is a factor that the DFT calculations ignored?",
                "answer_type": "Factoid",
                "answer": "These calculations ignored temperature effects that may reduce the significance of these energy differences."
            },
            {
                "question_type": "Comparative/Trend",
                "question": "How do the activation energies for both precursors compare for different substrates?",
                "answer_type": "Paragraph",
                "answer": "The \u0394E values for the SiH3\u2212NH2 and SiH3\u2212NH\u2212SiH3 models were almost identical, indicating the similar chemistry of primary (NH2) and secondary (NH) amine\ngroups. The transition state energy barriers or activation energies for SiH2(NH2)2 and SiH2DMA2 are quite similar to Eact for both precursors,  with the SiH3\u2212OH substrate lower than with SiH3\u2212NH2/SiH3\u2212NH\u2212SiH3 substrates."
            }
        ]
    },
    "bbox": {
        "a": {
            "x": 3,
            "y": 0,
            "width": 370,
            "height": 458
        },
        "b": {
            "x": 367,
            "y": 0,
            "width": 300,
            "height": 456
        }
    }
}