{
    "sample_id": "atomic-layer-deposition/simulation-usecase/8/figure_15",
    "classification": {
        "a": "multiple line chart"
    },
    "summarization": {
        "a": "The line chart illustrates the fraction of vacant lattice sites along the z-axis at various temperatures. Where the different temperatures result in different profiles also related to GPC."
    },
    "data_extraction": {
        "a": "| z-axis / angstrom | 27 \u00b0C | 52 \u00b0C | 77 \u00b0C | 127 \u00b0C | 177 \u00b0C |\n|---|---|---|---|---|---|\n| 0.00 | 0.00 | 0.00 | 0.00 | 0.00 | 0.00 |\n| 5.00 | 0.60 | 0.30 | 0.28 | 0.25 | 0.20 |\n| 10.00 | 0.75 | 0.28 | 0.25 | 0.15 | 0.15 |\n| 15.00 | 0.95 | 0.40 | 0.25 | 0.15 | 0.15 |\n| 20.00 | 1.00 | 0.70 | 0.25 | 0.15 | 0.15 |\n| 25.00 | 1.00 | 0.95 | 0.50 | 0.15 | 0.15 |\n| 30.00 | 1.00 | 1.00 | 0.95 | 0.75 | 0.75 |\n| 35.00 | 1.00 | 1.00 | 1.00 | 1.00 | 1.00 |\n| 40.00 | 1.00 | 1.00 | 1.00 | 1.00 | 1.00 |"
    },
    "vqa": {
        "a": [
            {
                "question_type": "Comparative/Trend",
                "question": "If the line reaches the value 1, what does this mean for the growth?",
                "answer_type": "Paragraph",
                "answer": "a\tIt seems that if the line reaches the value 1 this represents that the growth has stopped, indicating that for higher temperature the film thickness increases."
            },
            {
                "question_type": "Structure-Property",
                "question": "Where in the grown film are the most vacancies present?",
                "answer_type": "Paragraph",
                "answer": "a\tAt the interface between the starting surface and at the surface."
            },
            {
                "question_type": "Structure-Property",
                "question": "How thick is the surface layer with many vacancies according to this figure?",
                "answer_type": "Paragraph",
                "answer": "a\tAbout 10 angstrom for the process' at 127 and 177 degrees. The rest of the material shows little vacancies and can be seen as the bulk."
            },
            {
                "question_type": "Application/Performance",
                "question": "Why are vacancies unwanted?",
                "answer_type": "Paragraph",
                "answer": "a\tVacancies in the lattice structure can act as charge traps, resulting in lower performances."
            }
        ]
    },
    "bbox": {
        "a": {
            "x": 3,
            "y": 4,
            "width": 612,
            "height": 482
        }
    }
}