{
    "sample_id": "atomic-layer-deposition/experimental-usecase/38/figure_2",
    "classification": {
        "a": "multi spectra chart",
        "b": "multi spectra chart",
        "c": "multi spectra chart",
        "d": "multi spectra chart"
    },
    "summarization": {
        "a": "The figure shows the concentration of O, Mn, Si, and Li at different depths for MnO\u2082",
        "b": "The figure shows the concentration of O, Mn, Si, and Li at different depths for 10cLi-MnO\u2082",
        "c": "The figure shows the concentration of O, Mn, Si, and Li at different depths for 50cLi-MnO\u2082",
        "d": "The figure shows the concentration of O, Mn, Si, and Li at different depths for 100cLi-MnO\u2082",
        "e": "The figure shows the concentration of O, Mn, Si, and Li at different depths  for 200cLi-MnO\u2082",
        "f": "The figure shows the concentration of O, Mn, Si, and Li at different depths for 300cLi-MnO\u2082."
    },
    "data_extraction": {
        "a": "| Depth (x10^15 at/cm\u00b2) | O | Mn | Si | Li |\n|---|---|---|---|---|\n| 0 | 0 | 0 | 0 | 0 |\n| 500 | 60 | 50 | 40 | 30 |\n| 1000 | 60 | 50 | 40 | 30 |\n| 1500 | 60 | 50 | 40 | 30 |\n| 2000 | 60 | 50 | 40 | 30 |\n| 2500 | 60 | 50 | 40 | 30 |",
        "b": "| Depth (x10^15 at/cm\u00b2) | O | Mn | Si | Li |\n|---|---|---|---|---|\n| 0 | 60 | 50 | 40 | 30 |\n| 500 | 60 | 50 | 40 | 30 |\n| 1000 | 60 | 50 | 40 | 30 |\n| 1500 | 60 | 50 | 40 | 30 |\n| 2000 | 60 | 50 | 40 | 30 |\n| 2500 | 60 | 50 | 40 | 30 |",
        "c": "| Depth (x10^15 at/cm\u00b2) | O | Mn | Si | Li |\n|---|---|---|---|---|\n| 0 | 60 | 50 | 40 | 30 |\n| 500 | 60 | 50 | 40 | 30 |\n| 1000 | 60 | 50 | 40 | 30 |\n| 1500 | 60 | 50 | 40 | 30 |\n| 2000 | 60 | 50 | 40 | 30 |\n| 2500 | 60 | 50 | 40 | 30 |",
        "d": "| Depth (x10^15 at/cm\u00b2) | O | Mn | Si | Li |\n|---|---|---|---|---|\n| 0    | 60 | 50 | 40 | 10 |\n| 500  | 60 | 50 | 40 | 15 |\n| 1000 | 60 | 50 | 40 | 20 |\n| 1500 | 60 | 50 | 40 | 25 |\n| 2000 | 60 | 50 | 40 | 30 |",
        "e": "| Depth (x10^15 at/cm\u00b2) | O | Mn | Si | Li |\n|---|---|---|---|---|\n| 0    | 60 | 50 | 40 | 20 |\n| 500  | 60 | 50 | 40 | 25 |\n| 1000 | 60 | 50 | 40 | 30 |\n| 1500 | 60 | 50 | 40 | 35 |\n| 2000 | 60 | 50 | 40 | 40 |\n| 2500 | 60 | 50 | 40 | 40 |",
        "f": "| Depth (x10^15 at/cm\u00b2) | O | Mn | Si | Li |\n|---|---|---|---|---|\n| 0    | 60 | 50 | 40 | 30 |\n| 500  | 60 | 50 | 40 | 35 |\n| 1000 | 60 | 50 | 40 | 40 |\n| 1500 | 60 | 50 | 40 | 45 |\n| 2000 | 60 | 50 | 40 | 50 |\n| 2500 | 60 | 50 | 40 | 50 |"
    },
    "vqa": {
        "e": [
            {
                "question_type": "Process-Oriented",
                "question": "Does the lithiation appear homogeneously over the whole substrate?",
                "answer_type": "Yes/No",
                "answer": "Yes"
            }
        ],
        "d": [
            {
                "question_type": "Comparative/Trend",
                "question": "When does Lithium penetrate?",
                "answer_type": "Factoid",
                "answer": "In the samples 200cLi\u2212MnO2 and 300cLi\u2212MnO2, lithium is observed to penetrate throughout the whole film thickness."
            }
        ],
        "a": [
            {
                "question_type": "Comparative/Trend",
                "question": "Which figure corresponds to which sample?",
                "answer_type": "Paragraph",
                "answer": "The depth profiles correspond to the following samples\na. MnO2\nb. 10cLi-MnO2\nc. 50cLi-MnO2\nd. 100cLi-MnO2\ne. 200cLi-MnO2\nf. 300cLi-MnO2"
            }
        ],
        "b": [
            {
                "question_type": "Structure-Property",
                "question": "How is Lithium distributed across the films?",
                "answer_type": "Paragraph",
                "answer": "The depth profiles reveal that lithium is distributed only in the top part of the film in the samples 10cLi\u2212MnO2, 50cLi\u2212MnO2, and 100cLi\u2212MnO2, that is, when the average composition of the material is LixMn2O4, x \u2264 0.5. In the lithiated top parts of the films in these samples, the lithium concentrations were 0.6, 3.2, and 9.6 at. %, respectively."
            }
        ]
    },
    "bbox": {
        "a": {
            "x": 0,
            "y": 0,
            "width": 0,
            "height": 0
        },
        "b": {
            "x": 0,
            "y": 0,
            "width": 0,
            "height": 0
        },
        "c": {
            "x": 0,
            "y": 0,
            "width": 0,
            "height": 0
        },
        "d": {
            "x": 0,
            "y": 0,
            "width": 0,
            "height": 0
        }
    }
}