{
    "sample_id": "atomic-layer-deposition/experimental-usecase/45/figure_1",
    "classification": {
        "a": "multiple line chart"
    },
    "summarization": {
        "a": "The chart shows the thickness of materials deposited using different ALD methods (Remote plasma ALD Pt, Remote plasma ALD PtO\u2082, and Thermal ALD Pt) as a function of the number of cycles. Thermal Pt ALD shows no growth unless  applied after a Pt seed layer has been formed by remote plasma ALD. The remote plasma processes show near-linear thickness increase after a short initial nucleation period."
    },
    "data_extraction": {
        "a": "| Sample ID | Deposition mode and Material |  Number of cycles | Thickness (nm) | \n|---|---|---|---|\n| A | Thermal ALD Pt | 0 | 0 |\n| A | Thermal ALD Pt | 50 | 0.05 |\n| A | Thermal ALD Pt | 100 | 0.05 |\n| A | Thermal ALD Pt | 150 | 0.05 |\n| A | Thermal ALD Pt | 200 | 0.05 |\n| A | Thermal ALD Pt | 250 | 0.06 |\n| B | Remote plasma ALD PtO2| 0 | 0 |\n| B | Remote plasma ALD PtO2| 20 | 0.08 |\n| B | Remote plasma ALD PtO2| 30 | 0.37 |\n| B | Remote plasma ALD PtO2| 40 | 0.77 |\n| B | Remote plasma ALD PtO2| 50 | 1.47 |\n| B | Remote plasma ALD PtO2| 60 | 2.47 |\n| B | Remote plasma ALD PtO2| 130 | 4.92 |\n| B | Remote plasma ALD PtO2| 200 | 7.76 |\n| B | Remote plasma ALD PtO2| 250 | 9.98 |\n| C | Remote plasma ALD Pt| 0 | 0 |\n| C | Remote plasma ALD Pt| 20 | 0.52 |\n| C | Remote plasma ALD Pt| 40 | 1.43 |\n| C | Remote plasma ALD Pt| 60 | 2.99 |\n| C | Remote plasma ALD Pt| 100 | 5.07 |\n| C | Remote plasma ALD Pt| 150 | 7.23 |\n| C | Thermal ALD Pt| 160 | 7.45 |\n| C | Thermal ALD Pt| 200 | 8.97 |\n| C | Thermal ALD Pt| 250 | 10.89 |"
    },
    "vqa": {
        "a": [
            {
                "question_type": "Comparative/Trend",
                "question": "After approximately how many cycles does the PtO\u2082 indicates a constant growth-per-cycle?",
                "answer_type": "Factoid",
                "answer": "After approximately 50 cycles."
            },
            {
                "question_type": "Comparative/Trend",
                "question": "What evidence supports the conclusion that thermal ALD Pt growth occurs only after a Pt seed layer is formed by remote plasma ALD?",
                "answer_type": "Paragraph",
                "answer": "In the plot, thermal ALD Pt on the initial surface stays essentially at zero thickness over the full cycle range, indicating little to no growth. After 150 cycles of remote plasma ALD Pt, the process is switched to thermal ALD on the same sample and the thickness then increases steadily. This contrast shows that thermal ALD Pt growth proceeds when a Pt surface (seed layer) is present, but not on the starting  surface."
            },
            {
                "question_type": "Comparative/Trend",
                "question": "Which deposition process should be selected to reach at least 6 nm thickness of Pt in no more than 130 cycles?",
                "answer_type": "Factoid",
                "answer": "Remote plasma ALD Pt."
            },
            {
                "question_type": "Comparative/Trend",
                "question": "After approximately how many cycles does the plasma ALD Pt indicates a constant growth rate?",
                "answer_type": "Factoid",
                "answer": "After roughly 50 cycles."
            }
        ]
    },
    "bbox": {
        "a": {
            "x": 3,
            "y": 2,
            "width": 607,
            "height": 464
        }
    }
}